{
  "listResults": [
    {
      "zpid": "40.820274--72.81694",
      "id": "40.820274--72.81694",
      "providerListingId": "2k0r60wvfyfc3",
      "imgSrc": "https://photos.zillowstatic.com/fp/868c5b7b98433b524ef40592fb69967b-p_e.jpg",
      "hasImage": true,
      "detailUrl": "/apartments/moriches-ny/mirror-pond/5XpPZ2/",
      "statusType": "FOR_RENT",
      "statusText": "Mirror Pond",
      "address": "20 Mirror Ln, Moriches, NY",
      "addressStreet": "20 Mirror Ln # 1802",
      "addressCity": "Moriches",
      "addressState": "NY",
      "addressZipcode": "11955",
      "units": [
        {
          "price": "$3,334+",
          "beds": "2",
          "roomForRent": false
        }
      ],
      "lotId": 1001945875,
      "latLong": {
        "latitude": 40.820274,
        "longitude": -72.81694
      },
      "variableData": {
        "type": "TIME_ON_INFO",
        "text": "Updated yesterday"
      },
      "badgeInfo": {
        "type": "UNIT_AVAILABILITY",
        "text": "Unit availability"
      },
      "isSaved": false,
      "buildingName": "Mirror Pond",
      "isBuilding": true,
      "canSaveBuilding": true,
      "has3DModel": false,
      "isFeaturedListing": true,
      "isShowcaseListing": false,
      "list": true,
      "relaxed": false,
      "carouselPhotos": [
        {
          "url": "https://photos.zillowstatic.com/fp/868c5b7b98433b524ef40592fb69967b-p_e.jpg"
        },
        {
          "url": "https://photos.zillowstatic.com/fp/111139f6455d259900231f21dce649ed-p_e.jpg"
        },
        {
          "url": "https://photos.zillowstatic.com/fp/9196d24b70cead00ded7e140fe00ac5e-p_e.jpg"
        },
        {
          "url": "https://photos.zillowstatic.com/fp/aa7f321eb8b2eaeef82b40d02d9619ce-p_e.jpg"
        },
        {
          "url": "https://photos.zillowstatic.com/fp/c3176641842e96332900d3a6a3f0ced3-p_e.jpg"
        },
        {
          "url": "https://photos.zillowstatic.com/fp/a8a4b2b69124cad2e9a8981152f1f3e7-p_e.jpg"
        },
        {
          "url": "https://photos.zillowstatic.com/fp/8ade432895bed3fb6e9d2d57f6739773-p_e.jpg"
        },
        {
          "url": "https://photos.zillowstatic.com/fp/03a1082160cbaa1a7f43d48d27814d32-p_e.jpg"
        },
        {
          "url": "https://photos.zillowstatic.com/fp/e79814c59718198b5fb53be1bde4e535-p_e.jpg"
        },
        {
          "url": "https://photos.zillowstatic.com/fp/d0483ee32f6ad2615355dfee5e06cb15-p_e.jpg"
        },
        {
          "url": "https://photos.zillowstatic.com/fp/a85313d07a1026f014baef9a2bfcffbd-p_e.jpg"
        },
        {
          "url": "https://photos.zillowstatic.com/fp/2fc033994e57eb0111bd4b393f3da215-p_e.jpg"
        }
      ],
      "availabilityCount": 5,
      "marketingTreatments": [
        "trustedListing",
        "paid",
        "multiFamilySalesListing",
        "paidOrUnpaidMultifamily",
        "paidMultifamily"
      ],
      "isInstantTourEnabled": false,
      "isContactable": true
    },
    {
      "zpid": "40.806168--72.83673",
      "id": "40.806168--72.83673",
      "providerListingId": "9h3rx7snay63",
      "imgSrc": "https://photos.zillowstatic.com/fp/538046c6a668e8e17d7a73033cc52fe8-p_e.jpg",
      "hasImage": true,
      "detailUrl": "/apartments/mastic-ny/fairfield-lakeside-at-moriches/B9zcH2/",
      "statusType": "FOR_RENT",
      "statusText": "Fairfield Lakeside at Moriches",
      "address": "1775 Montauk Hwy, Mastic, NY",
      "addressStreet": "1775 Montauk Hwy  # 237726529",
      "addressCity": "Mastic",
      "addressState": "NY",
      "addressZipcode": "11950",
      "units": [
        {
          "price": "$2,055+",
          "beds": "1",
          "roomForRent": false
        },
        {
          "price": "$2,465+",
          "beds": "2",
          "roomForRent": false
        }
      ],
      "lotId": 2305875418,
      "latLong": {
        "latitude": 40.806168,
        "longitude": -72.83673
      },
      "variableData": {
        "type": "TIME_ON_INFO"
      },
      "badgeInfo": {
        "type": "UNIT_AVAILABILITY",
        "text": "Unit availability"
      },
      "isSaved": false,
      "buildingName": "Fairfield Lakeside at Moriches",
      "isBuilding": true,
      "canSaveBuilding": true,
      "has3DModel": false,
      "isFeaturedListing": true,
      "isShowcaseListing": false,
      "list": true,
      "relaxed": false,
      "carouselPhotos": [
        {
          "url": "https://photos.zillowstatic.com/fp/538046c6a668e8e17d7a73033cc52fe8-p_e.jpg"
        },
        {
          "url": "https://photos.zillowstatic.com/fp/aee95158f2d2b6ef3cd6cf460eb8c7f5-p_e.jpg"
        },
        {
          "url": "https://photos.zillowstatic.com/fp/e634b50b9f36d137ec4eeb169e3814d4-p_e.jpg"
        },
        {
          "url": "https://photos.zillowstatic.com/fp/6065d583ce52f4e3706b358d078d1dcc-p_e.jpg"
        },
        {
          "url": "https://photos.zillowstatic.com/fp/0309ea2bbf932b2a947119fc7d116b93-p_e.jpg"
        },
        {
          "url": "https://photos.zillowstatic.com/fp/c022d93c5e4827e8ce7d55e9d7ccd16f-p_e.jpg"
        },
        {
          "url": "https://photos.zillowstatic.com/fp/a6f48d736fc617b4e9c114778dffc738-p_e.jpg"
        },
        {
          "url": "https://photos.zillowstatic.com/fp/ff20aea78004a3f5432761b479428bd1-p_e.jpg"
        },
        {
          "url": "https://photos.zillowstatic.com/fp/9f9728c62245d38ef21c7516927aa688-p_e.jpg"
        },
        {
          "url": "https://photos.zillowstatic.com/fp/6a7544f55607c5a1274b6f01670581e2-p_e.jpg"
        },
        {
          "url": "https://photos.zillowstatic.com/fp/8d56126cfed61446dc6d50cff930b3aa-p_e.jpg"
        },
        {
          "url": "https://photos.zillowstatic.com/fp/02ec9305dee5cbbda22692ecd2714250-p_e.jpg"
        }
      ],
      "availabilityCount": 3,
      "marketingTreatments": [
        "trustedListing",
        "paid",
        "zillowRentalManager",
        "multiFamilySalesListing",
        "paidOrUnpaidMultifamily",
        "paidMultifamily",
        "multifamilyBasePackage"
      ],
      "isInstantTourEnabled": false,
      "isContactable": true
    },
    {
      "zpid": "59529912",
      "id": "59529912",
      "rawHomeStatusCd": "ForRent",
      "marketingStatusSimplifiedCd": "For Rent",
      "providerListingId": "4m1he35fpsap6",
      "imgSrc": "https://photos.zillowstatic.com/fp/8ccac8060cec5556d256d80f9b19e959-p_e.jpg",
      "hasImage": true,
      "detailUrl": "https://www.zillow.com/homedetails/31-Senix-Ave-Center-Moriches-NY-11934/59529912_zpid/",
      "statusType": "FOR_RENT",
      "statusText": "House for rent",
      "countryCurrency": "$",
      "price": "$16,000/mo",
      "unformattedPrice": 16000,
      "address": "31 Senix Ave, Center Moriches, NY 11934",
      "addressStreet": "31 Senix Ave",
      "addressCity": "Center Moriches",
      "addressState": "NY",
      "addressZipcode": "11934",
      "isUndisclosedAddress": false,
      "beds": 3,
      "baths": 3.0,
      "area": 2024,
      "latLong": {
        "latitude": 40.797295,
        "longitude": -72.80292
      },
      "isZillowOwned": false,
      "variableData": {
        "type": "TIME_ON_INFO",
        "data": {
          "isRead": null,
          "isFresh": false
        }
      },
      "hdpData": {
        "homeInfo": {
          "zpid": 59529912,
          "streetAddress": "31 Senix Ave",
          "zipcode": "11934",
          "city": "Center Moriches",
          "state": "NY",
          "latitude": 40.797295,
          "longitude": -72.80292,
          "price": 16000.0,
          "bathrooms": 3.0,
          "bedrooms": 3.0,
          "livingArea": 2024.0,
          "homeType": "SINGLE_FAMILY",
          "homeStatus": "FOR_RENT",
          "daysOnZillow": 112,
          "isFeatured": true,
          "shouldHighlight": false,
          "isRentalWithBasePrice": false,
          "zestimate": 821900,
          "rentZestimate": 5140,
          "listing_sub_type": {},
          "isUnmappable": false,
          "isPreforeclosureAuction": false,
          "homeStatusForHDP": "FOR_RENT",
          "priceForHDP": 16000.0,
          "timeOnZillow": 9690126000,
          "isNonOwnerOccupied": true,
          "isPremierBuilder": false,
          "isZillowOwned": false,
          "currency": "USD",
          "country": "USA",
          "taxAssessedValue": 481481.0,
          "isShowcaseListing": false
        }
      },
      "isSaved": false,
      "isUserClaimingOwner": false,
      "isUserConfirmedClaim": false,
      "pgapt": "ForRent",
      "sgapt": "For Rent",
      "zestimate": 821900,
      "shouldShowZestimateAsPrice": false,
      "has3DModel": false,
      "hasVideo": false,
      "isHomeRec": false,
      "hasAdditionalAttributions": true,
      "isFeaturedListing": true,
      "isShowcaseListing": false,
      "list": true,
      "relaxed": false,
      "brokerName": "Listing by: Coldwell Banker Reliable Real Estate",
      "carouselPhotos": [
        {
          "url": "https://photos.zillowstatic.com/fp/8ccac8060cec5556d256d80f9b19e959-p_e.jpg"
        },
        {
          "url": "https://photos.zillowstatic.com/fp/bf2ae48f42705a231a6ca60c40eec114-p_e.jpg"
        },
        {
          "url": "https://photos.zillowstatic.com/fp/e81a3b86d7f2089225c6a4cc757ae6e4-p_e.jpg"
        },
        {
          "url": "https://photos.zillowstatic.com/fp/3c9ab910f9c1f7d3af937866b1edcd8d-p_e.jpg"
        },
        {
          "url": "https://photos.zillowstatic.com/fp/6849c4189009aa19fe6e609e5a1b0a6d-p_e.jpg"
        },
        {
          "url": "https://photos.zillowstatic.com/fp/4ac50c115a4ce525a75f68fb0802443e-p_e.jpg"
        },
        {
          "url": "https://photos.zillowstatic.com/fp/7c558a623f24f77054f24b913f444d9c-p_e.jpg"
        },
        {
          "url": "https://photos.zillowstatic.com/fp/b96244a7f99969e6231def912ba049a0-p_e.jpg"
        },
        {
          "url": "https://photos.zillowstatic.com/fp/6e9b5d1c37f18eeabfe8b4f3de790006-p_e.jpg"
        },
        {
          "url": "https://photos.zillowstatic.com/fp/9e591ac42fb21fdc922409b88c042d1a-p_e.jpg"
        },
        {
          "url": "https://photos.zillowstatic.com/fp/530ac7a80c12c65eb7aa20bafa5a4782-p_e.jpg"
        },
        {
          "url": "https://photos.zillowstatic.com/fp/e061427cb78bb9129c35a4395cbea238-p_e.jpg"
        },
        {
          "url": "https://photos.zillowstatic.com/fp/40b72ceb7f5d3b01bfddbd790486c0b8-p_e.jpg"
        },
        {
          "url": "https://photos.zillowstatic.com/fp/0ed9c905bebddacf2b872f214dbe7fbc-p_e.jpg"
        },
        {
          "url": "https://photos.zillowstatic.com/fp/22e8e21848df06726fd0b6b84095c59e-p_e.jpg"
        },
        {
          "url": "https://photos.zillowstatic.com/fp/026884f1b8182e288cb98677cbbb643f-p_e.jpg"
        },
        {
          "url": "https://photos.zillowstatic.com/fp/ade7963aab7bb142367568189c7d3fbe-p_e.jpg"
        },
        {
          "url": "https://photos.zillowstatic.com/fp/e1710e02137459fdc47efea9aac5f809-p_e.jpg"
        },
        {
          "url": "https://photos.zillowstatic.com/fp/975908aa04886dc750bbbbf00dc7edb4-p_e.jpg"
        },
        {
          "url": "https://photos.zillowstatic.com/fp/658475f197b4670a4da2f0595039eb4b-p_e.jpg"
        },
        {
          "url": "https://photos.zillowstatic.com/fp/688fd810acd33c6688abfc63fe5fedbc-p_e.jpg"
        },
        {
          "url": "https://photos.zillowstatic.com/fp/b6f3c9cdc191dedaace23d62cdb1d753-p_e.jpg"
        },
        {
          "url": "https://photos.zillowstatic.com/fp/81d58f6be7a567ca874694b767bb1f87-p_e.jpg"
        },
        {
          "url": "https://photos.zillowstatic.com/fp/e42521c50e83debf4144997bcdde5dfa-p_e.jpg"
        },
        {
          "url": "https://photos.zillowstatic.com/fp/2058e1207fef9624f80446e387ccc913-p_e.jpg"
        },
        {
          "url": "https://photos.zillowstatic.com/fp/1d6c21616dd28fd69adeffe87c740b0c-p_e.jpg"
        },
        {
          "url": "https://photos.zillowstatic.com/fp/b9f45aaff2d53fc4ec07eace07fe50da-p_e.jpg"
        },
        {
          "url": "https://photos.zillowstatic.com/fp/33d6f174f89657db21be062042d53a87-p_e.jpg"
        }
      ],
      "marketingTreatments": [
        "paid"
      ],
      "rooms": []
    },
    {
      "zpid": "439898276",
      "id": "439898276",
      "rawHomeStatusCd": "ForRent",
      "marketingStatusSimplifiedCd": "For Rent",
      "providerListingId": "34eanhhygdknv",
      "imgSrc": "https://photos.zillowstatic.com/fp/a459e8e0592b3d41deb88fae4d46aeb1-p_e.jpg",
      "hasImage": true,
      "detailUrl": "https://www.zillow.com/homedetails/Moriches-NY-11955/439898276_zpid/",
      "statusType": "FOR_RENT",
      "statusText": "Apartment for rent",
      "countryCurrency": "$",
      "price": "$1,800/mo",
      "unformattedPrice": 1800,
      "address": "(undisclosed Address), Moriches, NY 11955",
      "addressStreet": "(undisclosed Address)",
      "addressCity": "Moriches",
      "addressState": "NY",
      "addressZipcode": "11955",
      "isUndisclosedAddress": true,
      "beds": 1,
      "baths": 1.0,
      "latLong": {},
      "isZillowOwned": false,
      "variableData": {
        "type": "TIME_ON_INFO",
        "text": "60 days ago",
        "data": {
          "isRead": null,
          "isFresh": false
        }
      },
      "hdpData": {
        "homeInfo": {
          "zpid": 439898276,
          "streetAddress": "(undisclosed Address)",
          "zipcode": "11955",
          "city": "Moriches",
          "state": "NY",
          "price": 1800.0,
          "datePriceChanged": 1729926000000,
          "bathrooms": 1.0,
          "bedrooms": 1.0,
          "homeType": "APARTMENT",
          "homeStatus": "FOR_RENT",
          "daysOnZillow": 60,
          "isFeatured": false,
          "shouldHighlight": false,
          "isRentalWithBasePrice": false,
          "listing_sub_type": {},
          "priceReduction": "$200 (Oct 26)",
          "isUnmappable": false,
          "isPreforeclosureAuction": false,
          "homeStatusForHDP": "FOR_RENT",
          "priceForHDP": 1800.0,
          "priceChange": -200,
          "timeOnZillow": 5188160000,
          "isNonOwnerOccupied": true,
          "isPremierBuilder": false,
          "isZillowOwned": false,
          "currency": "USD",
          "country": "USA",
          "isShowcaseListing": false
        }
      },
      "isSaved": false,
      "isUserClaimingOwner": false,
      "isUserConfirmedClaim": false,
      "pgapt": "ForRent",
      "sgapt": "For Rent",
      "shouldShowZestimateAsPrice": false,
      "has3DModel": false,
      "hasVideo": false,
      "isHomeRec": false,
      "hasAdditionalAttributions": true,
      "isFeaturedListing": false,
      "isShowcaseListing": false,
      "list": true,
      "relaxed": false,
      "brokerName": "Listing by: Approved Realty Services Corp",
      "carouselPhotos": [
        {
          "url": "https://photos.zillowstatic.com/fp/a459e8e0592b3d41deb88fae4d46aeb1-p_e.jpg"
        },
        {
          "url": "https://photos.zillowstatic.com/fp/203d64dea21118726b405da66b385bf1-p_e.jpg"
        },
        {
          "url": "https://photos.zillowstatic.com/fp/617eecf68491faf1ead706455ef1dc03-p_e.jpg"
        },
        {
          "url": "https://photos.zillowstatic.com/fp/8ef4ddf15a6545c7252aadf377bf198c-p_e.jpg"
        },
        {
          "url": "https://photos.zillowstatic.com/fp/7864d6c823871b4e16a93f2830fc539c-p_e.jpg"
        },
        {
          "url": "https://photos.zillowstatic.com/fp/218eb6c6ef7ecaa10827d14ca11b2091-p_e.jpg"
        }
      ],
      "marketingTreatments": [
        "zillowRentalManager"
      ],
      "rooms": []
    },
    {
      "zpid": "59534821",
      "id": "59534821",
      "rawHomeStatusCd": "ForRent",
      "marketingStatusSimplifiedCd": "For Rent",
      "providerListingId": "udezqkfhj4s7",
      "imgSrc": "https://photos.zillowstatic.com/fp/6800c5eaed109ff38341bd60306b88a2-p_e.jpg",
      "hasImage": true,
      "detailUrl": "https://www.zillow.com/homedetails/Center-Moriches-NY-11934/59534821_zpid/",
      "statusType": "FOR_RENT",
      "statusText": "Apartment for rent",
      "countryCurrency": "$",
      "price": "$14,000/mo",
      "unformattedPrice": 14000,
      "address": "(undisclosed Address), Center Moriches, NY 11934",
      "addressStreet": "(undisclosed Address)",
      "addressCity": "Center Moriches",
      "addressState": "NY",
      "addressZipcode": "11934",
      "isUndisclosedAddress": true,
      "beds": 3,
      "baths": 1.0,
      "latLong": {},
      "isZillowOwned": false,
      "variableData": {
        "type": "TIME_ON_INFO",
        "data": {
          "isRead": null,
          "isFresh": false
        }
      },
      "hdpData": {
        "homeInfo": {
          "zpid": 59534821,
          "streetAddress": "(undisclosed Address)",
          "zipcode": "11934",
          "city": "Center Moriches",
          "state": "NY",
          "price": 14000.0,
          "datePriceChanged": 1689577200000,
          "bathrooms": 1.0,
          "bedrooms": 3.0,
          "homeType": "MULTI_FAMILY",
          "homeStatus": "FOR_RENT",
          "daysOnZillow": 49,
          "isFeatured": true,
          "shouldHighlight": false,
          "isRentalWithBasePrice": false,
          "zestimate": 631600,
          "rentZestimate": 2659,
          "listing_sub_type": {},
          "isUnmappable": false,
          "isPreforeclosureAuction": false,
          "homeStatusForHDP": "FOR_RENT",
          "priceForHDP": 14000.0,
          "priceChange": 9800,
          "timeOnZillow": 4307942000,
          "isNonOwnerOccupied": true,
          "isPremierBuilder": false,
          "isZillowOwned": false,
          "currency": "USD",
          "country": "USA",
          "lotAreaValue": 0.36,
          "lotAreaUnit": "acres",
          "isShowcaseListing": false
        }
      },
      "isSaved": false,
      "isUserClaimingOwner": false,
      "isUserConfirmedClaim": false,
      "pgapt": "ForRent",
      "sgapt": "For Rent",
      "zestimate": 631600,
      "shouldShowZestimateAsPrice": false,
      "has3DModel": false,
      "hasVideo": false,
      "isHomeRec": false,
      "hasAdditionalAttributions": true,
      "isFeaturedListing": true,
      "isShowcaseListing": false,
      "list": true,
      "relaxed": false,
      "brokerName": "Listing by: Nest Seekers International",
      "carouselPhotos": [
        {
          "url": "https://photos.zillowstatic.com/fp/6800c5eaed109ff38341bd60306b88a2-p_e.jpg"
        },
        {
          "url": "https://photos.zillowstatic.com/fp/5b86e19b279b45ce662d09d3565522b9-p_e.jpg"
        },
        {
          "url": "https://photos.zillowstatic.com/fp/5dc9567c23b9caa73bbb6358dc8a5707-p_e.jpg"
        },
        {
          "url": "https://photos.zillowstatic.com/fp/9afec06625035ec9b9c49bed37918ad0-p_e.jpg"
        },
        {
          "url": "https://photos.zillowstatic.com/fp/a480799e240efc15ae065d12daa32c3c-p_e.jpg"
        },
        {
          "url": "https://photos.zillowstatic.com/fp/c24713ff7e0b94dbeb8fb886e3d13e33-p_e.jpg"
        },
        {
          "url": "https://photos.zillowstatic.com/fp/69df97642555d504b3c748740beaac1b-p_e.jpg"
        },
        {
          "url": "https://photos.zillowstatic.com/fp/d2612dfb62484711490780f0bf0d5dd8-p_e.jpg"
        },
        {
          "url": "https://photos.zillowstatic.com/fp/e8137d9c9b90bc2f4b60893281f36e91-p_e.jpg"
        },
        {
          "url": "https://photos.zillowstatic.com/fp/d9437aa278332f81b5c01f4e363ed474-p_e.jpg"
        },
        {
          "url": "https://photos.zillowstatic.com/fp/14f83df8483fe6ea2d640e5481c50b0c-p_e.jpg"
        },
        {
          "url": "https://photos.zillowstatic.com/fp/677184abe45ea97d91dea8053f8dd9ab-p_e.jpg"
        },
        {
          "url": "https://photos.zillowstatic.com/fp/49c3105047e4fda0f47485acf752619a-p_e.jpg"
        },
        {
          "url": "https://photos.zillowstatic.com/fp/fc8abe10ea63b2a1345c6fd24d9c61b0-p_e.jpg"
        },
        {
          "url": "https://photos.zillowstatic.com/fp/02a94b821af499a751dbc7324c6e4f44-p_e.jpg"
        },
        {
          "url": "https://photos.zillowstatic.com/fp/b5911868cca0d8028a0a74a5287d70c5-p_e.jpg"
        },
        {
          "url": "https://photos.zillowstatic.com/fp/4e10ebf0486147f564ca79c88dfc0b3b-p_e.jpg"
        },
        {
          "url": "https://photos.zillowstatic.com/fp/4ac469a4d73f935084b8cd68f06cfe38-p_e.jpg"
        },
        {
          "url": "https://photos.zillowstatic.com/fp/9948dd05825957ac362bbd2e90dd6ec5-p_e.jpg"
        },
        {
          "url": "https://photos.zillowstatic.com/fp/bff03f86ce73f8398242de707a2de24c-p_e.jpg"
        },
        {
          "url": "https://photos.zillowstatic.com/fp/100dfadd55ea2474b2dbb4288559aef6-p_e.jpg"
        },
        {
          "url": "https://photos.zillowstatic.com/fp/4f84a7cf156518c80a79f1fdea7355e0-p_e.jpg"
        }
      ],
      "marketingTreatments": [
        "paid"
      ],
      "rooms": []
    },
    {
      "zpid": "59331559",
      "id": "59331559",
      "rawHomeStatusCd": "ForRent",
      "marketingStatusSimplifiedCd": "For Rent",
      "providerListingId": "2scarckt2j0wj",
      "imgSrc": "https://photos.zillowstatic.com/fp/49548c6b3e4ac1979b2a6d70bd7eb71a-p_e.jpg",
      "hasImage": true,
      "detailUrl": "https://www.zillow.com/homedetails/12-Dundalk-Rd-Manorville-NY-11949/59331559_zpid/",
      "statusType": "FOR_RENT",
      "statusText": "House for rent",
      "countryCurrency": "$",
      "price": "$3,500/mo",
      "unformattedPrice": 3500,
      "address": "12 Dundalk Rd, Manorville, NY 11949",
      "addressStreet": "12 Dundalk Rd",
      "addressCity": "Manorville",
      "addressState": "NY",
      "addressZipcode": "11949",
      "isUndisclosedAddress": false,
      "beds": 4,
      "baths": 2.0,
      "latLong": {
        "latitude": 40.82259,
        "longitude": -72.83205
      },
      "isZillowOwned": false,
      "variableData": {
        "type": "TIME_ON_INFO",
        "text": "9 days ago",
        "data": {
          "isRead": null,
          "isFresh": false
        }
      },
      "hdpData": {
        "homeInfo": {
          "zpid": 59331559,
          "streetAddress": "12 Dundalk Rd",
          "zipcode": "11949",
          "city": "Manorville",
          "state": "NY",
          "latitude": 40.82259,
          "longitude": -72.83205,
          "price": 3500.0,
          "bathrooms": 2.0,
          "bedrooms": 4.0,
          "homeType": "SINGLE_FAMILY",
          "homeStatus": "FOR_RENT",
          "daysOnZillow": 9,
          "isFeatured": false,
          "shouldHighlight": false,
          "isRentalWithBasePrice": false,
          "zestimate": 595700,
          "rentZestimate": 3638,
          "listing_sub_type": {},
          "isUnmappable": false,
          "isPreforeclosureAuction": false,
          "homeStatusForHDP": "FOR_RENT",
          "priceForHDP": 3500.0,
          "timeOnZillow": 810102000,
          "isNonOwnerOccupied": true,
          "isPremierBuilder": false,
          "isZillowOwned": false,
          "currency": "USD",
          "country": "USA",
          "taxAssessedValue": 537037.0,
          "isShowcaseListing": false
        }
      },
      "isSaved": false,
      "isUserClaimingOwner": false,
      "isUserConfirmedClaim": false,
      "pgapt": "ForRent",
      "sgapt": "For Rent",
      "zestimate": 595700,
      "shouldShowZestimateAsPrice": false,
      "has3DModel": false,
      "hasVideo": false,
      "isHomeRec": false,
      "hasAdditionalAttributions": true,
      "isFeaturedListing": false,
      "isShowcaseListing": false,
      "list": true,
      "relaxed": false,
      "brokerName": "Listing by: Moriches Bay Realty",
      "carouselPhotos": [
        {
          "url": "https://photos.zillowstatic.com/fp/49548c6b3e4ac1979b2a6d70bd7eb71a-p_e.jpg"
        },
        {
          "url": "https://photos.zillowstatic.com/fp/a69da666113d598809840685323f1957-p_e.jpg"
        }
      ],
      "rooms": []
    },
    {
      "zpid": "59524293",
      "id": "59524293",
      "rawHomeStatusCd": "ForRent",
      "marketingStatusSimplifiedCd": "For Rent",
      "providerListingId": "2ajz2krqp7z7k",
      "imgSrc": "https://photos.zillowstatic.com/fp/bce492411f3fcdc3d85ed80559762767-p_e.jpg",
      "hasImage": true,
      "detailUrl": "https://www.zillow.com/homedetails/1-Barnes-Rd-Moriches-NY-11955/59524293_zpid/",
      "statusType": "FOR_RENT",
      "statusText": "Apartment for rent",
      "countryCurrency": "$",
      "price": "$3,000/mo",
      "unformattedPrice": 3000,
      "address": "1 Barnes Rd, Moriches, NY 11955",
      "addressStreet": "1 Barnes Rd",
      "addressCity": "Moriches",
      "addressState": "NY",
      "addressZipcode": "11955",
      "isUndisclosedAddress": false,
      "beds": 3,
      "baths": 1.0,
      "area": 1048,
      "latLong": {
        "latitude": 40.807907,
        "longitude": -72.83317
      },
      "isZillowOwned": false,
      "variableData": {
        "type": "TIME_ON_INFO",
        "text": "61 days ago",
        "data": {
          "isRead": null,
          "isFresh": false
        }
      },
      "hdpData": {
        "homeInfo": {
          "zpid": 59524293,
          "streetAddress": "1 Barnes Rd",
          "zipcode": "11955",
          "city": "Moriches",
          "state": "NY",
          "latitude": 40.807907,
          "longitude": -72.83317,
          "price": 3000.0,
          "bathrooms": 1.0,
          "bedrooms": 3.0,
          "livingArea": 1048.0,
          "homeType": "APARTMENT",
          "homeStatus": "FOR_RENT",
          "daysOnZillow": 61,
          "isFeatured": false,
          "shouldHighlight": false,
          "isRentalWithBasePrice": false,
          "rentZestimate": 2582,
          "listing_sub_type": {},
          "isUnmappable": false,
          "isPreforeclosureAuction": false,
          "homeStatusForHDP": "FOR_RENT",
          "priceForHDP": 3000.0,
          "timeOnZillow": 5295456000,
          "isNonOwnerOccupied": true,
          "isPremierBuilder": false,
          "isZillowOwned": false,
          "currency": "USD",
          "country": "USA",
          "taxAssessedValue": 439815.0,
          "isShowcaseListing": false
        }
      },
      "isSaved": false,
      "isUserClaimingOwner": false,
      "isUserConfirmedClaim": false,
      "pgapt": "ForRent",
      "sgapt": "For Rent",
      "shouldShowZestimateAsPrice": false,
      "has3DModel": false,
      "hasVideo": false,
      "isHomeRec": false,
      "hasAdditionalAttributions": true,
      "isFeaturedListing": false,
      "isShowcaseListing": false,
      "list": true,
      "relaxed": false,
      "brokerName": "Listing by: Approved Realty Services Corp",
      "carouselPhotos": [
        {
          "url": "https://photos.zillowstatic.com/fp/bce492411f3fcdc3d85ed80559762767-p_e.jpg"
        },
        {
          "url": "https://photos.zillowstatic.com/fp/b03b438ae805c22be59f3125b7cfa154-p_e.jpg"
        },
        {
          "url": "https://photos.zillowstatic.com/fp/f864892f7aa485bee841a9464b9779cb-p_e.jpg"
        },
        {
          "url": "https://photos.zillowstatic.com/fp/30b08205a45015c66c073afad512c4b8-p_e.jpg"
        },
        {
          "url": "https://photos.zillowstatic.com/fp/084a344cb7f6f55714e442b328595289-p_e.jpg"
        },
        {
          "url": "https://photos.zillowstatic.com/fp/c04ad17c8de4d78f1805ff6743476f2b-p_e.jpg"
        },
        {
          "url": "https://photos.zillowstatic.com/fp/476c22b618d33ebfbc98ac520cf1903d-p_e.jpg"
        },
        {
          "url": "https://photos.zillowstatic.com/fp/4072d8c58073354e84dac61b6e92dd97-p_e.jpg"
        },
        {
          "url": "https://photos.zillowstatic.com/fp/ce69d015fcacce8ca7fae2efea84b437-p_e.jpg"
        },
        {
          "url": "https://photos.zillowstatic.com/fp/b9506c5872c2ac695d35d43daaa969ba-p_e.jpg"
        },
        {
          "url": "https://photos.zillowstatic.com/fp/9af5ffd547f523a11b7bc435b6655790-p_e.jpg"
        },
        {
          "url": "https://photos.zillowstatic.com/fp/94d0bc5f4bed10a3b09ca165b63028b5-p_e.jpg"
        },
        {
          "url": "https://photos.zillowstatic.com/fp/11b4bda1feba94cd1dc8aafc03c1cf47-p_e.jpg"
        }
      ],
      "marketingTreatments": [
        "zillowRentalManager"
      ],
      "rooms": []
    },
    {
      "zpid": "40.81855--72.82053",
      "id": "40.81855--72.82053",
      "providerListingId": "3wa0dtkb07b30",
      "imgSrc": "https://photos.zillowstatic.com/fp/3f7bb4776643b4ebcd1b5e540dd9f40f-p_e.jpg",
      "hasImage": true,
      "detailUrl": "/apartments/moriches-ny/pine-hills-south/C3xFWY/",
      "statusType": "FOR_RENT",
      "statusText": "Pine Hills South",
      "address": "1B Meadowoods Ln, Moriches, NY",
      "addressStreet": "1B Meadowoods Ln # 6217",
      "addressCity": "Moriches",
      "addressState": "NY",
      "addressZipcode": "11955",
      "units": [
        {
          "price": "$2,155+",
          "beds": "1",
          "roomForRent": false
        },
        {
          "price": "$2,656+",
          "beds": "2",
          "roomForRent": false
        }
      ],
      "lotId": 2553481559,
      "latLong": {
        "latitude": 40.81855,
        "longitude": -72.82053
      },
      "variableData": {
        "type": "TIME_ON_INFO",
        "text": "Updated yesterday"
      },
      "badgeInfo": {
        "type": "UNIT_AVAILABILITY",
        "text": "Unit availability"
      },
      "isSaved": false,
      "buildingName": "Pine Hills South",
      "isBuilding": true,
      "canSaveBuilding": true,
      "has3DModel": false,
      "isFeaturedListing": true,
      "isShowcaseListing": false,
      "list": true,
      "relaxed": false,
      "carouselPhotos": [
        {
          "url": "https://photos.zillowstatic.com/fp/3f7bb4776643b4ebcd1b5e540dd9f40f-p_e.jpg"
        },
        {
          "url": "https://photos.zillowstatic.com/fp/b669bca95adb586996f0e29957f989c4-p_e.jpg"
        },
        {
          "url": "https://photos.zillowstatic.com/fp/9934141c7276dcf8efd2ccc4ab7d2613-p_e.jpg"
        },
        {
          "url": "https://photos.zillowstatic.com/fp/dccccb4d444ac17f004e08bf6d43a408-p_e.jpg"
        },
        {
          "url": "https://photos.zillowstatic.com/fp/9094f2b6c90c596659ac482675213333-p_e.jpg"
        },
        {
          "url": "https://photos.zillowstatic.com/fp/252049c66c486901cae303617565207d-p_e.jpg"
        },
        {
          "url": "https://photos.zillowstatic.com/fp/62ea31c4ac0aa6847e93ca8298b96a8f-p_e.jpg"
        },
        {
          "url": "https://photos.zillowstatic.com/fp/b3fdd37948f7c7c5ddad8b2a1c241ab3-p_e.jpg"
        },
        {
          "url": "https://photos.zillowstatic.com/fp/db0e074607f23a987740bd14cf8be3aa-p_e.jpg"
        },
        {
          "url": "https://photos.zillowstatic.com/fp/a332d067652044810dbdb0e9fddf771a-p_e.jpg"
        },
        {
          "url": "https://photos.zillowstatic.com/fp/59af485f7d1d23f2c59da36f1cd25bde-p_e.jpg"
        },
        {
          "url": "https://photos.zillowstatic.com/fp/8434ba6ac134317d8ece03c72567840c-p_e.jpg"
        }
      ],
      "availabilityCount": 22,
      "marketingTreatments": [
        "trustedListing",
        "paid",
        "multiFamilySalesListing",
        "paidOrUnpaidMultifamily",
        "paidMultifamily"
      ],
      "isInstantTourEnabled": false,
      "isContactable": true
    }
  ],
  "mapResults": [
    {
      "plid": "2k0r60wvfyfc3",
      "imgSrc": "https://photos.zillowstatic.com/fp/868c5b7b98433b524ef40592fb69967b-p_e.jpg",
      "hasImage": true,
      "detailUrl": "/apartments/moriches-ny/mirror-pond/5XpPZ2/",
      "statusType": "FOR_RENT",
      "statusText": "Mirror Pond",
      "price": "$3,334+/mo",
      "address": "20 Mirror Ln, Moriches, NY",
      "minBeds": 2,
      "minBaths": 2.0,
      "minArea": 1195,
      "lotId": 1001945875,
      "latLong": {
        "latitude": 40.820274,
        "longitude": -72.81694
      },
      "variableData": {
        "type": "TIME_ON_INFO",
        "text": "Updated yesterday"
      },
      "badgeInfo": {
        "type": "UNIT_AVAILABILITY",
        "text": "Unit availability"
      },
      "buildingName": "Mirror Pond",
      "buildingId": "40.820274--72.81694",
      "isBuilding": true,
      "canSaveBuilding": true,
      "has3DModel": false,
      "isHomeRec": false,
      "hasAdditionalAttributions": false,
      "isFeaturedListing": true,
      "isShowcaseListing": false,
      "listingType": "",
      "isFavorite": false,
      "timeOnZillow": 115897000,
      "unitCount": 5,
      "rentalMarketingSubType": "unknown",
      "marketingTreatments": [
        "trustedListing",
        "paid",
        "multiFamilySalesListing",
        "paidOrUnpaidMultifamily",
        "paidMultifamily"
      ]
    },
    {
      "plid": "9h3rx7snay63",
      "imgSrc": "https://photos.zillowstatic.com/fp/538046c6a668e8e17d7a73033cc52fe8-p_e.jpg",
      "hasImage": true,
      "detailUrl": "/apartments/mastic-ny/fairfield-lakeside-at-moriches/B9zcH2/",
      "statusType": "FOR_RENT",
      "statusText": "Fairfield Lakeside at Moriches",
      "price": "$2,055+/mo",
      "address": "1775 Montauk Hwy, Mastic, NY",
      "minBeds": 1,
      "minBaths": 1.0,
      "lotId": 2305875418,
      "latLong": {
        "latitude": 40.806168,
        "longitude": -72.83673
      },
      "variableData": {
        "type": "TIME_ON_INFO"
      },
      "badgeInfo": {
        "type": "UNIT_AVAILABILITY",
        "text": "Unit availability"
      },
      "buildingName": "Fairfield Lakeside at Moriches",
      "buildingId": "40.806168--72.83673",
      "isBuilding": true,
      "canSaveBuilding": true,
      "has3DModel": false,
      "isHomeRec": false,
      "hasAdditionalAttributions": false,
      "isFeaturedListing": true,
      "isShowcaseListing": false,
      "listingType": "",
      "isFavorite": false,
      "timeOnZillow": 4325709000,
      "unitCount": 3,
      "rentalMarketingSubType": "unknown",
      "marketingTreatments": [
        "trustedListing",
        "paid",
        "zillowRentalManager",
        "multiFamilySalesListing",
        "paidOrUnpaidMultifamily",
        "paidMultifamily",
        "multifamilyBasePackage"
      ]
    },
    {
      "zpid": "59529912",
      "rawHomeStatusCd": "ForRent",
      "marketingStatusSimplifiedCd": "For Rent",
      "imgSrc": "https://photos.zillowstatic.com/fp/8ccac8060cec5556d256d80f9b19e959-p_e.jpg",
      "hasImage": true,
      "detailUrl": "/homedetails/31-Senix-Ave-Center-Moriches-NY-11934/59529912_zpid/",
      "statusType": "FOR_RENT",
      "statusText": "House for rent",
      "price": "$16,000/mo",
      "priceLabel": "$16K",
      "address": "31 Senix Ave, Center Moriches, NY 11934",
      "isNewYorkState": true,
      "beds": 3,
      "baths": 3.0,
      "area": 2024,
      "latLong": {
        "latitude": 40.797295,
        "longitude": -72.80292
      },
      "variableData": {
        "type": "TIME_ON_INFO",
        "data": {
          "isRead": null,
          "isFresh": false
        }
      },
      "hdpData": {
        "homeInfo": {
          "zpid": 59529912,
          "streetAddress": "31 Senix Ave",
          "zipcode": "11934",
          "city": "Center Moriches",
          "state": "NY",
          "latitude": 40.797295,
          "longitude": -72.80292,
          "price": 16000.0,
          "bathrooms": 3.0,
          "bedrooms": 3.0,
          "livingArea": 2024.0,
          "homeType": "SINGLE_FAMILY",
          "homeStatus": "FOR_RENT",
          "daysOnZillow": -1,
          "isFeatured": true,
          "shouldHighlight": false,
          "isRentalWithBasePrice": false,
          "zestimate": 821900,
          "rentZestimate": 5140,
          "listing_sub_type": {},
          "isUnmappable": false,
          "isPreforeclosureAuction": false,
          "homeStatusForHDP": "FOR_RENT",
          "priceForHDP": 16000.0,
          "timeOnZillow": 9690126000,
          "isNonOwnerOccupied": true,
          "isPremierBuilder": false,
          "isZillowOwned": false,
          "currency": "USD",
          "country": "USA",
          "taxAssessedValue": 481481.0,
          "isShowcaseListing": false
        }
      },
      "isUserClaimingOwner": false,
      "isUserConfirmedClaim": false,
      "pgapt": "ForRent",
      "sgapt": "For Rent",
      "shouldShowZestimateAsPrice": false,
      "has3DModel": false,
      "hasVideo": false,
      "isHomeRec": false,
      "hasAdditionalAttributions": true,
      "isFeaturedListing": true,
      "isShowcaseListing": false,
      "listingType": "",
      "isFavorite": false,
      "visited": false,
      "brokerName": "Listing by: Coldwell Banker Reliable Real Estate",
      "timeOnZillow": 9690126000,
      "rentalMarketingSubType": "unknown",
      "marketingTreatments": [
        "paid"
      ]
    },
    {
      "zpid": "59331559",
      "rawHomeStatusCd": "ForRent",
      "marketingStatusSimplifiedCd": "For Rent",
      "imgSrc": "https://photos.zillowstatic.com/fp/49548c6b3e4ac1979b2a6d70bd7eb71a-p_e.jpg",
      "hasImage": true,
      "detailUrl": "/homedetails/12-Dundalk-Rd-Manorville-NY-11949/59331559_zpid/",
      "statusType": "FOR_RENT",
      "statusText": "House for rent",
      "price": "$3,500/mo",
      "priceLabel": "$3.5K",
      "address": "12 Dundalk Rd, Manorville, NY 11949",
      "isNewYorkState": true,
      "beds": 4,
      "baths": 2.0,
      "latLong": {
        "latitude": 40.82259,
        "longitude": -72.83205
      },
      "variableData": {
        "type": "TIME_ON_INFO",
        "text": "9 days ago",
        "data": {
          "isRead": null,
          "isFresh": false
        }
      },
      "hdpData": {
        "homeInfo": {
          "zpid": 59331559,
          "streetAddress": "12 Dundalk Rd",
          "zipcode": "11949",
          "city": "Manorville",
          "state": "NY",
          "latitude": 40.82259,
          "longitude": -72.83205,
          "price": 3500.0,
          "bathrooms": 2.0,
          "bedrooms": 4.0,
          "homeType": "SINGLE_FAMILY",
          "homeStatus": "FOR_RENT",
          "daysOnZillow": -1,
          "isFeatured": false,
          "shouldHighlight": false,
          "isRentalWithBasePrice": false,
          "zestimate": 595700,
          "rentZestimate": 3638,
          "listing_sub_type": {},
          "isUnmappable": false,
          "isPreforeclosureAuction": false,
          "homeStatusForHDP": "FOR_RENT",
          "priceForHDP": 3500.0,
          "timeOnZillow": 810102000,
          "isNonOwnerOccupied": true,
          "isPremierBuilder": false,
          "isZillowOwned": false,
          "currency": "USD",
          "country": "USA",
          "taxAssessedValue": 537037.0,
          "isShowcaseListing": false
        }
      },
      "isUserClaimingOwner": false,
      "isUserConfirmedClaim": false,
      "pgapt": "ForRent",
      "sgapt": "For Rent",
      "shouldShowZestimateAsPrice": false,
      "has3DModel": false,
      "hasVideo": false,
      "isHomeRec": false,
      "hasAdditionalAttributions": true,
      "isFeaturedListing": false,
      "isShowcaseListing": false,
      "listingType": "",
      "isFavorite": false,
      "visited": false,
      "brokerName": "Listing by: Moriches Bay Realty",
      "timeOnZillow": 810102000,
      "rentalMarketingSubType": "unknown"
    },
    {
      "zpid": "59524293",
      "rawHomeStatusCd": "ForRent",
      "marketingStatusSimplifiedCd": "For Rent",
      "imgSrc": "https://photos.zillowstatic.com/fp/bce492411f3fcdc3d85ed80559762767-p_e.jpg",
      "hasImage": true,
      "detailUrl": "/homedetails/1-Barnes-Rd-Moriches-NY-11955/59524293_zpid/",
      "statusType": "FOR_RENT",
      "statusText": "Apartment for rent",
      "price": "$3,000/mo",
      "priceLabel": "$3.0K",
      "address": "1 Barnes Rd, Moriches, NY 11955",
      "isNewYorkState": true,
      "beds": 3,
      "baths": 1.0,
      "area": 1048,
      "latLong": {
        "latitude": 40.807907,
        "longitude": -72.83317
      },
      "variableData": {
        "type": "TIME_ON_INFO",
        "text": "61 days ago",
        "data": {
          "isRead": null,
          "isFresh": false
        }
      },
      "hdpData": {
        "homeInfo": {
          "zpid": 59524293,
          "streetAddress": "1 Barnes Rd",
          "zipcode": "11955",
          "city": "Moriches",
          "state": "NY",
          "latitude": 40.807907,
          "longitude": -72.83317,
          "price": 3000.0,
          "bathrooms": 1.0,
          "bedrooms": 3.0,
          "livingArea": 1048.0,
          "homeType": "APARTMENT",
          "homeStatus": "FOR_RENT",
          "daysOnZillow": -1,
          "isFeatured": false,
          "shouldHighlight": false,
          "isRentalWithBasePrice": false,
          "rentZestimate": 2582,
          "listing_sub_type": {},
          "isUnmappable": false,
          "isPreforeclosureAuction": false,
          "homeStatusForHDP": "FOR_RENT",
          "priceForHDP": 3000.0,
          "timeOnZillow": 5295456000,
          "isNonOwnerOccupied": true,
          "isPremierBuilder": false,
          "isZillowOwned": false,
          "currency": "USD",
          "country": "USA",
          "taxAssessedValue": 439815.0,
          "isShowcaseListing": false
        }
      },
      "isUserClaimingOwner": false,
      "isUserConfirmedClaim": false,
      "pgapt": "ForRent",
      "sgapt": "For Rent",
      "shouldShowZestimateAsPrice": false,
      "has3DModel": false,
      "hasVideo": false,
      "isHomeRec": false,
      "hasAdditionalAttributions": true,
      "isFeaturedListing": false,
      "isShowcaseListing": false,
      "listingType": "",
      "isFavorite": false,
      "visited": false,
      "brokerName": "Listing by: Approved Realty Services Corp",
      "timeOnZillow": 5295456000,
      "rentalMarketingSubType": "unknown",
      "marketingTreatments": [
        "zillowRentalManager"
      ]
    },
    {
      "plid": "3wa0dtkb07b30",
      "imgSrc": "https://photos.zillowstatic.com/fp/3f7bb4776643b4ebcd1b5e540dd9f40f-p_e.jpg",
      "hasImage": true,
      "detailUrl": "/apartments/moriches-ny/pine-hills-south/C3xFWY/",
      "statusType": "FOR_RENT",
      "statusText": "Pine Hills South",
      "price": "$2,155+/mo",
      "address": "1B Meadowoods Ln, Moriches, NY",
      "minBeds": 1,
      "minBaths": 1.0,
      "minArea": 864,
      "lotId": 2553481559,
      "latLong": {
        "latitude": 40.81855,
        "longitude": -72.82053
      },
      "variableData": {
        "type": "TIME_ON_INFO",
        "text": "Updated yesterday"
      },
      "badgeInfo": {
        "type": "UNIT_AVAILABILITY",
        "text": "Unit availability"
      },
      "buildingName": "Pine Hills South",
      "buildingId": "40.81855--72.82053",
      "isBuilding": true,
      "canSaveBuilding": true,
      "has3DModel": false,
      "isHomeRec": false,
      "hasAdditionalAttributions": false,
      "isFeaturedListing": true,
      "isShowcaseListing": false,
      "listingType": "",
      "isFavorite": false,
      "timeOnZillow": 115858000,
      "unitCount": 22,
      "rentalMarketingSubType": "unknown",
      "marketingTreatments": [
        "trustedListing",
        "paid",
        "multiFamilySalesListing",
        "paidOrUnpaidMultifamily",
        "paidMultifamily"
      ]
    }
  ],
  "relaxedResults": [],
  "resultsHash": "586ac22a",
  "showForYouCount": 0,
  "relaxedResultsHash": "1"
}